lecrapaud/__init__.py
lecrapaud/base.py
lecrapaud/config.py
lecrapaud/db/__init__.py
lecrapaud/db/alembic/README
lecrapaud/db/alembic/env.py
lecrapaud/db/alembic/script.py.mako
lecrapaud/db/alembic/versions/2025_06_23_1748-f089dfb7e3ba_.py
lecrapaud/db/alembic/versions/2025_06_24_1216-c62251b129ed_.py
lecrapaud/db/alembic/versions/2025_06_24_1711-86457e2f333f_.py
lecrapaud/db/alembic/versions/2025_06_25_1759-72aa496ca65b_.py
lecrapaud/db/alembic/versions/2025_08_25_1434-7ed9963e732f_add_best_score_to_model_selection.py
lecrapaud/db/alembic/versions/2025_08_28_1516-c36e9fee22b9_add_avg_precision_to_score.py
lecrapaud/db/alembic/versions/2025_08_28_1622-8b11c1ba982e_change_name_column.py
lecrapaud/db/alembic/versions/2025_10_25_0635-07e303521594_add_unique_constraint_to_score.py
lecrapaud/db/alembic/versions/2025_10_26_1727-033e0f7eca4f_merge_score_and_model_trainings_into_.py
lecrapaud/db/alembic/versions/2025_10_28_2006-0a8fb7826e9b_add_number_of_targets_and_remove_other_.py
lecrapaud/db/alembic/versions/2025_12_16_1644-9a191ae1c27d_add_bias_to_score.py
lecrapaud/db/alembic/versions/2025_12_20_1915-99108bd42b68_add_score_to_experiment.py
lecrapaud/db/alembic/versions/2026_01_21_1814-a1b2c3d4e5f6_add_artifact_storage.py
lecrapaud/db/alembic/versions/2026_01_21_1830-b2c3d4e5f6g7_migrate_files_to_db.py
lecrapaud/db/alembic/versions/2026_01_26_1942-f723ecc52b89_rename_model_to_model_type.py
lecrapaud/db/alembic/versions/2026_01_26_2120-080475ab231a_rename_model_selection_to_best_model.py
lecrapaud/db/alembic/versions/2026_01_28_1427-dc9b28c3e796_fix_wrong_model_type_for_classification.py
lecrapaud/db/alembic/versions/2026_01_28_1616-721327520692_remove_best_prefix_from_best_model.py
lecrapaud/db/alembic/versions/2026_01_28_1721-0e47cb122c58_fix_method_names.py
lecrapaud/db/alembic.ini
lecrapaud/db/session.py
lecrapaud/directories.py
lecrapaud/experiment.py
lecrapaud/feature_engineering.py
lecrapaud/feature_preprocessing.py
lecrapaud/feature_selection.py
lecrapaud-0.27.26.dist-info/METADATA
lecrapaud-0.27.26.dist-info/WHEEL
lecrapaud-0.27.26.dist-info/licenses/LICENSE
lecrapaud-0.27.26.dist-info/RECORD
