Metadata-Version: 2.4
Name: lecrapaud
Version: 0.27.26
Summary: Framework for machine and deep learning, with regression, classification and time series analysis
License: Apache License
License-File: LICENSE
Author: Pierre H. Gallet
Requires-Python: ==3.12.*
Classifier: License :: Other/Proprietary License
Classifier: Programming Language :: Python :: 3
Classifier: Programming Language :: Python :: 3.12
Requires-Dist: alembic (>=1.17.2)
Requires-Dist: bandit (>=1.9.2)
Requires-Dist: black (>=25.12.0)
Requires-Dist: catboost (>=1.2.8)
Requires-Dist: category-encoders (>=2.9.0)
Requires-Dist: codecov (>=2.1.13)
Requires-Dist: coverage (>=7.13.0)
Requires-Dist: flake8 (>=7.3.0)
Requires-Dist: ftfy (>=6.3.1)
Requires-Dist: hyperopt (>=0.2.7)
Requires-Dist: ipykernel (>=7.1.0)
Requires-Dist: ipywidgets (>=8.1.8)
Requires-Dist: joblib (>=1.5.3)
Requires-Dist: keras (>=3.12.0)
Requires-Dist: keras-tcn (>=3.5.6)
Requires-Dist: lightgbm (>=4.6.0)
Requires-Dist: lime (>=0.2.0.1)
Requires-Dist: matplotlib (>=3.10.8)
Requires-Dist: mkdocs (>=1.6.0)
Requires-Dist: mkdocs-gen-files (>=0.5.0)
Requires-Dist: mkdocs-literate-nav (>=0.6.0)
Requires-Dist: mkdocs-material (>=9.5.0)
Requires-Dist: mkdocs-section-index (>=0.3.8)
Requires-Dist: mkdocstrings[python] (>=0.27.0)
Requires-Dist: mlxtend (>=0.23.4)
Requires-Dist: mypy (>=1.19.1)
Requires-Dist: numpy (>=2.1.3)
Requires-Dist: openai (>=2.13.0)
Requires-Dist: pandas (>=2.3.3)
Requires-Dist: pipdeptree (>=2.30.0)
Requires-Dist: poetry (>=2.2.1)
Requires-Dist: pydantic (>=2.12.5)
Requires-Dist: pylint (>=4.0.4)
Requires-Dist: pymysql (>=1.1.2)
Requires-Dist: pytest (>=9.0.2)
Requires-Dist: pytest-cov (>=7.0.0)
Requires-Dist: pytest-mock (>=3.15.1)
Requires-Dist: python-dotenv (>=1.2.1)
Requires-Dist: ray[tune] (>=2.52.1)
Requires-Dist: safety (>=3.7.0)
Requires-Dist: scikit-learn (>=1.6.1)
Requires-Dist: scipy (>=1.16.3)
Requires-Dist: seaborn (>=0.13.2)
Requires-Dist: sentry-sdk (>=2.48.0)
Requires-Dist: shap (>=0.50.0)
Requires-Dist: sqlalchemy (>=2.0.45)
Requires-Dist: tabulate (>=0.9.0)
Requires-Dist: tensorboard (<=2.19.0)
Requires-Dist: tensorboardx (>=2.6.4)
Requires-Dist: tensorflow (<=2.19.0)
Requires-Dist: tiktoken (>=0.12.0)
Requires-Dist: tqdm (>=4.67.1)
Requires-Dist: xgboost (>=3.1.2)
